pk_calculator/__init__.py
pk_calculator/main.py
pk_calculator-0.5.dist-info/METADATA
pk_calculator-0.5.dist-info/WHEEL
pk_calculator-0.5.dist-info/top_level.txt
pk_calculator-0.5.dist-info/RECORD
